[
  {
    "id": 1,
    "title": "Casio Scientific Calculator FX-570EX",
    "description": "Reliable used scientific calculator suitable for secondary and college students. Fully functional with minor cosmetic wear.",
    "category": ["stationery"],
    "price": 999999.99,
    "discountPercentage": 10,
    "rating": 4.5,
    "stock": 10,
    "tags": ["calculator", "used", "school"],
    "brand": "Casio",
    "sku": "STA-CAS-CAL-001",
    "weight": 200,
    "dimensions": {
      "width": 7,
      "height": 16,
      "depth": 1.5
    },
    "warrantyInformation": "1 month warranty",
    "shippingInformation": "Ships in 3-5 business days",
    "availabilityStatus": "In Stock",
    "reviews": [
      {
        "rating": 5,
        "comment": "Works perfectly and great value for money!",
        "date": "2025-04-30T09:41:02.053Z",
        "reviewerName": "Amirul Rahman",
        "reviewerEmail": "amirul.rahman@x.dummyjson.com"
      }
    ],
    "returnPolicy": "7 days return policy",
    "minimumOrderQuantity": 1,
    "meta": {
      "createdAt": "2025-04-30T09:41:02.053Z",
      "updatedAt": "2025-04-30T09:41:02.053Z",
      "barcode": "9551234567890",
      "qrCode": "https://cdn.dummyjson.com/public/qr-code.png"
    },
    "images": ["/calc.png"],
    "thumbnail": "/calc.png"
  },
  {
    "id": 2,
    "title": "A4 Ring Binder File (Used)",
    "description": "Durable used binder in good condition, perfect for organizing class notes and assignments.",
    "category": ["stationery"],
    "price": 67.67,
    "discountPercentage": 10,
    "rating": 4.2,
    "stock": 30,
    "tags": ["file", "binder", "used"],
    "brand": "No Brand",
    "sku": "STA-FIL-BIN-002",
    "weight": 300,
    "dimensions": {
      "width": 25,
      "height": 32,
      "depth": 4
    },
    "warrantyInformation": "No warranty",
    "shippingInformation": "Ships in 3 days",
    "availabilityStatus": "In Stock",
    "reviews": [
      {
        "rating": 4,
        "comment": "Clean and still very usable!",
        "date": "2025-04-30T09:41:02.053Z",
        "reviewerName": "Sarah Lee",
        "reviewerEmail": "sarah.lee@x.dummyjson.com"
      }
    ],
    "returnPolicy": "No return policy",
    "minimumOrderQuantity": 2,
    "meta": {
      "createdAt": "2025-04-30T09:41:02.053Z",
      "updatedAt": "2025-04-30T09:41:02.053Z",
      "barcode": "9550987654321",
      "qrCode": "https://cdn.dummyjson.com/public/qr-code.png"
    },
    "images": ["/binder.jpg"],
    "thumbnail": "/binder.jpg"
  },
  {
    "id": 3,
    "title": "Used Mechanical Pencil Set",
    "description": "Set of 14 mechanical pencils in working condition, suitable for everyday school use.",
    "category": ["stationery"],
    "price": 1299.99,
    "discountPercentage": 10,
    "rating": 4,
    "stock": 20,
    "tags": ["pencil", "used", "writing"],
    "brand": "Pentel",
    "sku": "STA-PEN-MEC-003",
    "weight": 50,
    "dimensions": {
      "width": 5,
      "height": 15,
      "depth": 1
    },
    "warrantyInformation": "No warranty",
    "shippingInformation": "Ships in 2-4 business days",
    "availabilityStatus": "In Stock",
    "reviews": [
      {
        "rating": 4,
        "comment": "Slightly worn but still writes smoothly!",
        "date": "2025-04-30T09:41:02.053Z",
        "reviewerName": "Jenson Ohh",
        "reviewerEmail": "jason.tan@x.dummyjson.com"
      }
    ],
    "returnPolicy": "7 days return policy",
    "minimumOrderQuantity": 1,
    "meta": {
      "createdAt": "2025-04-30T09:41:02.053Z",
      "updatedAt": "2025-04-30T09:41:02.053Z",
      "barcode": "9556543217890",
      "qrCode": "https://cdn.dummyjson.com/public/qr-code.png"
    },
    "images": ["/mechpencils.jpg"],
    "thumbnail": "/mechpencils.jpg"
  },
  {
    "id": 4,
    "title": "Used School Bag (Standard Size)",
    "description": "Gently used school bag with spacious compartments. Suitable for primary or secondary school students.",
    "category": ["used-items"],
    "price": 999.99,
    "discountPercentage": 10,
    "rating": 4.3,
    "stock": 5,
    "tags": ["bag", "used", "school"],
    "brand": "Nike",
    "sku": "USE-BAG-SCH-004",
    "weight": 700,
    "dimensions": {
      "width": 30,
      "height": 45,
      "depth": 15
    },
    "warrantyInformation": "No warranty",
    "shippingInformation": "Ships in 5 days",
    "availabilityStatus": "Low Stock",
    "reviews": [
      {
        "rating": 5,
        "comment": "Still in great condition and comfortable to carry!",
        "date": "2025-04-30T09:41:02.053Z",
        "reviewerName": "Nur Ellysha",
        "reviewerEmail": "nur.aisyah@x.dummyjson.com"
      }
    ],
    "returnPolicy": "No return policy",
    "minimumOrderQuantity": 1,
    "meta": {
      "createdAt": "2025-04-30T09:41:02.053Z",
      "updatedAt": "2025-04-30T09:41:02.053Z",
      "barcode": "9553344556677",
      "qrCode": "https://cdn.dummyjson.com/public/qr-code.png"
    },
    "images": ["/schoolbag.jpg"],
    "thumbnail": "/schoolbag.jpg"
  },
  {
    "id": 5,
    "title": "Used Water Bottle 500ml",
    "description": "Reusable 500ml water bottle, cleaned and sanitized. Ideal for school use.",
    "category": ["used-items"],
    "price": 499.99,
    "discountPercentage": 10,
    "rating": 3.9,
    "stock": 15,
    "tags": ["bottle", "used", "eco-friendly"],
    "brand": "Tupperware",
    "sku": "USE-BOT-WAT-005",
    "weight": 120,
    "dimensions": {
      "width": 7,
      "height": 20,
      "depth": 7
    },
    "warrantyInformation": "No warranty",
    "shippingInformation": "Ships in 3-5 business days",
    "availabilityStatus": "In Stock",
    "reviews": [
      {
        "rating": 4,
        "comment": "Good condition and very clean.",
        "date": "2025-04-30T09:41:02.053Z",
        "reviewerName": "John Nathan Chow",
        "reviewerEmail": "adrian.lim@x.dummyjson.com"
      }
    ],
    "returnPolicy": "No return policy",
    "minimumOrderQuantity": 1,
    "meta": {
      "createdAt": "2025-04-30T09:41:02.053Z",
      "updatedAt": "2025-04-30T09:41:02.053Z",
      "barcode": "9557766554433",
      "qrCode": "https://cdn.dummyjson.com/public/qr-code.png"
    },
    "images": ["/waterbottle.jpg"],
    "thumbnail": "/waterbottle.jpg"
  },
  {
    "id": 6,
    "title": "Half-Used Faber Castell Pen",
    "description": "Enjoy the smoothest performance and a stylish new look, this isn’t just a pen - it’s your vibe. For the cheap price of only 199. Sourced from 'journalists' in class.",
    "category": ["stationery", "used-items"],
    "price": 199.99,
    "discountPercentage": 10,
    "rating": 4.67,
    "stock": 30,
    "tags": ["pens", "used", "school"],
    "brand": "Faber-Castell",
    "sku": "STA-CAS-CAL-001",
    "weight": 50,
    "dimensions": {
      "width": 7,
      "height": 25,
      "depth": 1.5
    },
    "warrantyInformation": "1 month warranty",
    "shippingInformation": "Ships in 6-7 business days",
    "availabilityStatus": "In Stock",
    "reviews": [
      {
        "rating": 5,
        "comment": "Writes smoothly and amazing value for money! Must buy for all students.",
        "date": "2025-04-30T09:41:02.053Z",
        "reviewerName": "Nigel Said",
        "reviewerEmail": "nigel.richards@x.dummyjson.com"
      }
    ],
    "returnPolicy": "3 days return policy",
    "minimumOrderQuantity": 1,
    "meta": {
      "createdAt": "2025-04-30T09:41:02.053Z",
      "updatedAt": "2025-04-30T09:41:02.053Z",
      "barcode": "9551234567890",
      "qrCode": "https://cdn.dummyjson.com/public/qr-code.png"
    },
    "images": ["/pen.jpg"],
    "thumbnail": "/pen.jpg"
  },
  {
    "id": 7,
    "title": "Mixue Lemonade Drink",
    "description": "Mixue Lemonade originated from a passion for crafting the perfect citrus drink. The journey began with a vision to create a beverage that goes beyond the ordinary. For all 80% and above scorers, they can earn a Mixue Lemonade, free of charge!",
    "category": ["drinks"],
    "price": 2.99,
    "discountPercentage": 100,
    "rating": 5,
    "stock": 33,
    "tags": ["drinks", "reward"],
    "brand": "Mixue",
    "weight": 300,
    "dimensions": {
      "width": 7,
      "height": 19,
      "depth": 1.5
    },
    "warrantyInformation": "No warranty",
    "shippingInformation": "Immediate shipping",
    "availabilityStatus": "Out of Stock, check back for Mid-Years",
    "reviews": [
      {
        "rating": 4.8,
        "comment": "Great drink and good target for all Math students!",
        "date": "2025-04-30T09:41:02.053Z",
        "reviewerName": "Lucas Jothin",
        "reviewerEmail": "wesleyan.student@x.dummyjson.com"
      }
    ],
    "returnPolicy": "1 minute return policy",
    "minimumOrderQuantity": 1,
    "maximumOrderQuantity": 1,
    "meta": {
      "createdAt": "2025-04-30T09:41:02.053Z",
      "updatedAt": "2025-04-30T09:41:02.053Z",
      "barcode": "9551234567890",
      "qrCode": "https://cdn.dummyjson.com/public/qr-code.png"
    },
    "images": ["/mixue.jpg"],
    "thumbnail": "/mixue.jpg"
  },
  {
    "id": 8,
    "title": "Artline 500A Whiteboard Marker Medium Point 6 Colours",
    "description": "Writing on the whiteboard has never been easier! With the Artline 500A Whiteboard Marker Medium Point, you can now answer the teacher's questions on the board without borrowing their marker and making them annoyed! A set of 6 markers for only RM20.",
    "category": ["stationery"],
    "price": 299.99,
    "discountPercentage": 10,
    "rating": 4.2,
    "stock": 50,
    "tags": "stationery",
    "brand": "Artline",
    "weight": 200,
    "dimensions": {
      "width": 7,
      "height": 19,
      "depth": 1.5
    },
    "warrantyInformation": "No warranty",
    "shippingInformation": "Shipping in 6-7 working days",
    "availabilityStatus": "In Stock",
    "reviews": [
      {
        "rating": 4.2,
        "comment": "Great marker pen! I can now answer questions on the board without getting another nagging from my teacher to get my own whiteboard marker.",
        "date": "2025-04-30T09:41:02.053Z",
        "reviewerName": "Bartholomew, John",
        "reviewerEmail": "john.bartholomew@x.dummyjson.com"
      }
    ],
    "returnPolicy": "1 week return policy",
    "minimumOrderQuantity": 1,
    "meta": {
      "createdAt": "2025-04-30T09:41:02.053Z",
      "updatedAt": "2025-04-30T09:41:02.053Z",
      "barcode": "9551234567890",
      "qrCode": "https://cdn.dummyjson.com/public/qr-code.png"
    },
    "images": ["/marker.jpg"],
    "thumbnail": "/marker.jpg"
  },
  {
    "id": 9,
    "title": "Exclusive Wesleyan A5 Exercise Book",
    "description": "An A5 Exercise Book to do your homework and write notes in! For only the cheap price of RM1, storing your notes in the exclusive Wesley cover has never been easier. Pro Tip: Buy multiple books so your homework doesn't get eaten by your dog!",
    "category": ["stationery", "exclusive-items"],
    "price": 19.99,
    "discountPercentage": 10,
    "rating": 3.9,
    "stock": 100,
    "tags": "stationery",
    "brand": "Wesley Exclusive",
    "weight": 50,
    "dimensions": {
      "width": 7,
      "height": 19,
      "depth": 1.5
    },
    "warrantyInformation": "No warranty",
    "shippingInformation": "Shipping in 2-3 working days",
    "availabilityStatus": "In Stock",
    "reviews": [
      {
        "rating": 4,
        "comment": "Great notebook for writing all my notes down. This helped me pass Math for the first time!",
        "date": "2025-04-30T09:41:02.053Z",
        "reviewerName": "James Lin",
        "reviewerEmail": "james.wong@x.dummyjson.com"
      },
      {
        "rating": 3.8,
        "comment": "Good notebook for doing homework in. However, I bought 5 books and all 5 got eaten by my dog. Next time, make the book bigger pls, thanks.",
        "date": "2025-04-30T09:41:02.053Z",
        "reviewerName": "Chan Wei Ong",
        "reviewerEmail": "chan.wei.cong@x.dummyjson.com"
      }
    ],
    "returnPolicy": "1 week return policy",
    "minimumOrderQuantity": 3,
    "meta": {
      "createdAt": "2025-04-30T09:41:02.053Z",
      "updatedAt": "2025-04-30T09:41:02.053Z",
      "barcode": "9551234567890",
      "qrCode": "https://cdn.dummyjson.com/public/qr-code.png"
    },
    "images": ["/exercisebook.jpg"],
    "thumbnail": "/exercisebook.jpg"
  },
  {
    "id": 10,
    "title": "Elroy's Exclusive Drumsticks",
    "description": "Elroy's Exclusive drum sticks were molded under strict quality control standards from carefully selected wood materials and is renowned for their consistent high quality. Get this premium and exclusive drumsticks for only RM 1999!",
    "category": ["exclusive-items"],
    "price": 1999.99,
    "discountPercentage": 0.00001,
    "rating": 5,
    "stock": 1,
    "tags": ["exclusive-items"],
    "brand": "Elroy Exclusive",
    "weight": 100,
    "dimensions": {
      "width": 7,
      "height": 19,
      "depth": 1.5
    },
    "warrantyInformation": "3 month warranty",
    "shippingInformation": "Shipping in 4-5 working days",
    "availabilityStatus": "In Stock",
    "reviews": [
      {
        "rating": 5,
        "comment": "Amazing drumsticks! Now I can shred on my drums and play (i mean use) it in school!",
        "date": "2025-04-30T09:41:02.053Z",
        "reviewerName": "Goh Jern Han",
        "reviewerEmail": "goh.jern.han@x.dummyjson.com"
      }
    ],
    "returnPolicy": "1 week return policy",
    "minimumOrderQuantity": 1,
    "meta": {
      "createdAt": "2025-04-30T09:41:02.053Z",
      "updatedAt": "2025-04-30T09:41:02.053Z",
      "barcode": "9551234567890",
      "qrCode": "https://cdn.dummyjson.com/public/qr-code.png"
    },
    "images": ["/drumsticks.jpg"],
    "thumbnail": "/drumsticks.jpg"
  },
  {
    "id": 11,
    "title": "BuniMart Optic Glasses",
    "description": "BuniMart Optic Glasses are glasses designed for ease of use and all-day wearability. Made by the renouned Ms. Buni, and crafted from titanium.",
    "category": ["exclusive-items"],
    "price": 1999.99,
    "discountPercentage": 20,
    "rating": 5,
    "stock": 10,
    "tags": ["exclusive-items"],
    "brand": "BuniMart Exclusive",
    "weight": 100,
    "dimensions": {
      "width": 7,
      "height": 19,
      "depth": 1.5
    },
    "warrantyInformation": "1 year warranty",
    "shippingInformation": "Shipping in 4-5 working days",
    "availabilityStatus": "In Stock",
    "reviews": [
      {
        "rating": 5,
        "comment": "Absolutely incredible quality, buy two if you need them!",
        "date": "2025-04-30T09:41:02.053Z",
        "reviewerName": "Ms. Buni",
        "reviewerEmail": "goh.jern.han@x.dummyjson.com"
      },
      {
        "rating": 5,
        "comment": "I really need these!",
        "date": "2025-04-30T09:41:02.053Z",
        "reviewerName": "Tan Dong Jiu",
        "reviewerEmail": "goh.jern.han@x.dummyjson.com"
      }
    ],
    "returnPolicy": "1 week return policy",
    "minimumOrderQuantity": 1,
    "meta": {
      "createdAt": "2025-04-30T09:41:02.053Z",
      "updatedAt": "2025-04-30T09:41:02.053Z",
      "barcode": "9551234567890",
      "qrCode": "https://cdn.dummyjson.com/public/qr-code.png"
    },
    "images": ["/glasses.jpg"],
    "thumbnail": "/glasses.jpg"
  },
  {
    "id": 12,
    "title": "Save BuniMart!",
    "description": "Dawn Lim Sim Zheng of 10 Genesis has hacked BuniMart. RM 99999999999999999999999999999999999999999999999999 (not too overpriced for BuniMart) to get back BuniMart or else it will be destroyed forever. This message will self-destruct in 3 days.",
    "category": [
      "exclusive-items",
      "stationery",
      "used-items",
      "reward",
      "drinks"
    ],
    "price": 1e50,
    "discountPercentage": 0,
    "rating": 5,
    "stock": 1,
    "tags": ["exclusive-items", "stationery", "used-items", "reward", "drinks"],
    "brand": "Dawn Exclusive",
    "warrantyInformation": "1 year warranty",
    "shippingInformation": "Online Shipping via Website",
    "availabilityStatus": "In Stock",
    "reviews": [
      {
        "rating": 5,
        "comment": "There's no way anyone would pay RM 99999999999999999999999999999999999999999999999999 for BuniMart! BuniMart is MINE!",
        "date": "2025-04-30T09:41:02.053Z",
        "reviewerName": "Dawn Lim",
        "reviewerEmail": "dawn.lim@x.dummyjson.com"
      }
    ],
    "returnPolicy": "3 days return policy",
    "minimumOrderQuantity": 1,
    "meta": {
      "createdAt": "2025-04-30T09:41:02.053Z",
      "updatedAt": "2025-04-30T09:41:02.053Z",
      "barcode": "9551234567890",
      "qrCode": "https://cdn.dummyjson.com/public/qr-code.png"
    },
    "images": ["/hack.jpg"],
    "thumbnail": "/hack.jpg"
  },
  {
    "id": 13,
    "title": "Graph Paper",
    "description": "Standard A4 graph paper suitable for math, geometry and geometry dash sketches.",
    "category": ["stationery"],
    "price": 2.5,
    "discountPercentage": 10,
    "rating": 4.8,
    "stock": 120,
    "tags": ["stationery"],
    "brand": "BuniMart Exclusive",
    "warrantyInformation": "No warranty (consumable item)",
    "shippingInformation": "Standard delivery via courier",
    "availabilityStatus": "In Stock",
    "reviews": [
      {
        "rating": 5,
        "comment": "Good quality paper and accurate grid layout.",
        "date": "2025-04-30T09:41:02.053Z",
        "reviewerName": "Lychee Wayne",
        "reviewerEmail": "alex.tan@x.dummyjson.com"
      }
    ],
    "returnPolicy": "7-day return for unused items",
    "minimumOrderQuantity": 1,
    "meta": {
      "createdAt": "2025-04-30T09:41:02.053Z",
      "updatedAt": "2025-04-30T09:41:02.053Z",
      "barcode": "9551234567890",
      "qrCode": "https://cdn.dummyjson.com/public/qr-code.png"
    },
    "images": ["/graphpaper.jpg"],
    "thumbnail": "/graphpaper.jpg"
  }
]
